{
    "version": 1,
    "id": "the-dwarven-kingdom-6505",
    "spec": {
        "name": "The Entrance To The Mountain",
        "description": "Here is an entrance to the mountain. The door looks very well built, and you can hear noise coming from within.",
        "zone_id": "the-dwarven-kingdom",
        "exits": {
            "east": {
                "room_id": "the-dwarven-kingdom-6503"
            },
            "west": {
                "room_id": "the-dwarven-kingdom-6513",
                "closure": {
                    "name": "door",
                    "closed": true,
                    "lock": {
                        "key_id": "the-dwarven-kingdom-6515",
                        "locked": true,
                        "pickproof": true
                    }
                }
            }
        }
    }
}
