{
    "version": 1,
    "id": "the-dwarven-kingdom-6514",
    "spec": {
        "name": "The Path",
        "description": "You are on a path in the dwarven village which leads north to the shops and south to the corner of the area.",
        "zone_id": "the-dwarven-kingdom",
        "exits": {
            "north": {
                "room_id": "the-dwarven-kingdom-6515"
            },
            "south": {
                "room_id": "the-dwarven-kingdom-6513"
            }
        }
    },
    "circlemud_unused": {
        "sector_type": "INSIDE",
        "flags": [
            "INDOORS"
        ]
    }
}
