{
    "version": 1,
    "id": "rome-12017",
    "spec": {
        "name": "The Lion Pit",
        "description": "As you land at the bottom of this dirt-walled pit, the realization that a pit full of lions is NOT a good thing to be hanging around in. Several of the gladiators gather around the edge of the pit to watch your demise. You look around you, and all you see is tawny fur and gaping jaws... it is too late to run, too late to hide. Twelve lions rip you and your belongings into a gory mass of bloodied leather, bronze, and bone. What's that old saying? Cats killed the curious? Something like that, I'm sure...",
        "zone_id": "rome",
        "exits": {
            "up": {
                "room_id": "rome-12010"
            },
            "down": {
                "room_id": "rome-12016"
            }
        },
        "perks": [
            {
                "type": "grant",
                "key": "room_death"
            }
        ]
    },
    "circlemud_unused": {
        "sector_type": "INSIDE",
        "flags": [
            "INDOORS"
        ]
    }
}
