{
    "version": 1,
    "id": "dwarf-35",
    "spec": {
        "name": "Dwarf",
        "abbreviation": "Dw",
        "perks": [
            {
                "type": "grant",
                "key": "wear_slot",
                "arg": "light"
            },
            {
                "type": "grant",
                "key": "wear_slot",
                "arg": "head"
            },
            {
                "type": "grant",
                "key": "wear_slot",
                "arg": "neck"
            },
            {
                "type": "grant",
                "key": "wear_slot",
                "arg": "neck"
            },
            {
                "type": "grant",
                "key": "wear_slot",
                "arg": "about"
            },
            {
                "type": "grant",
                "key": "wear_slot",
                "arg": "body"
            },
            {
                "type": "grant",
                "key": "wear_slot",
                "arg": "arms"
            },
            {
                "type": "grant",
                "key": "wear_slot",
                "arg": "wrist"
            },
            {
                "type": "grant",
                "key": "wear_slot",
                "arg": "wrist"
            },
            {
                "type": "grant",
                "key": "wear_slot",
                "arg": "hands"
            },
            {
                "type": "grant",
                "key": "wear_slot",
                "arg": "finger"
            },
            {
                "type": "grant",
                "key": "wear_slot",
                "arg": "finger"
            },
            {
                "type": "grant",
                "key": "wear_slot",
                "arg": "wield"
            },
            {
                "type": "grant",
                "key": "wear_slot",
                "arg": "off_hand"
            },
            {
                "type": "grant",
                "key": "wear_slot",
                "arg": "hold"
            },
            {
                "type": "grant",
                "key": "wear_slot",
                "arg": "waist"
            },
            {
                "type": "grant",
                "key": "wear_slot",
                "arg": "legs"
            },
            {
                "type": "grant",
                "key": "wear_slot",
                "arg": "feet"
            },
            {
                "type": "modifier",
                "key": "core.stats.con",
                "value": 2
            },
            {
                "type": "modifier",
                "key": "core.stats.cha",
                "value": -2
            },
            {
                "type": "modifier",
                "key": "core.resource.hp.max",
                "value": 20
            },
            {
                "type": "modifier",
                "key": "core.resource.hp.per_level",
                "value": 5
            },
            {
                "type": "modifier",
                "key": "core.resource.hp.regen",
                "value": 1
            },
            {
                "type": "modifier",
                "key": "core.resource.mana.max",
                "value": 30
            },
            {
                "type": "modifier",
                "key": "core.resource.mana.per_level",
                "value": 3
            },
            {
                "type": "modifier",
                "key": "core.resource.mana.regen",
                "value": 2
            },
            {
                "type": "modifier",
                "key": "core.combat.ac.flat",
                "value": 10
            },
            {
                "type": "modifier",
                "key": "core.action_points.max",
                "value": 1
            },
            {
                "type": "modifier",
                "key": "core.action_points.max",
                "value": 1
            },
            {
                "type": "grant",
                "key": "ignore_restriction",
                "arg": "room_dark"
            },
            {
                "type": "grant",
                "key": "unlock_ability",
                "arg": "attack"
            },
            {
                "type": "grant",
                "key": "unlock_ability",
                "arg": "fireball"
            },
            {
                "type": "grant",
                "key": "unlock_ability",
                "arg": "flame-ward"
            },
            {
                "type": "grant",
                "key": "unlock_ability",
                "arg": "bash"
            }
        ]
    }
}
