{
    "version": 1,
    "id": "the-high-tower-of-magic-2539",
    "spec": {
        "name": "The Burnt Room",
        "description": "You are in what looks to have once been a guest bed room. The walls are blackened and burnt by what you could only imagine to be magical fire. There is no sign of the previous occupant, undoubtedly he left in a hurry. The only exit leads back west to the hallway.",
        "zone_id": "the-high-tower-of-magic",
        "exits": {
            "west": {
                "room_id": "the-high-tower-of-magic-2538",
                "closure": {
                    "name": "door",
                    "closed": true
                }
            }
        },
        "perks": [
            {
                "type": "grant",
                "key": "dark"
            }
        ]
    }
}
